{
  "type": "FeatureCollection",
  "features": [
    {
      "type": "Feature",
      "geometry": {
        "type": "Point",
        "coordinates": [
          8.638927213543438,
          49.85750935735035
        ]
      },
      "properties": {
        "name": "Quartierladen",
        "category": "building"
      }
    },
    {
      "type": "Feature",
      "properties": {
        "name": "?",
        "category": "building"
      },
      "geometry": {
        "type": "Point",
        "coordinates": [
          8.639100193977356,
          49.85653719416691
        ]
      }
    },
    {
      "type": "Feature",
      "properties": {
        "name": "Kiosk",
        "category": "building"
      },
      "geometry": {
        "type": "Point",
        "coordinates": [
          8.642954528331757,
          49.858200684840604
        ]
      }
    },
    {
      "type": "Feature",
      "properties": {
        "category": "playground",
        "name": "Spielplatz"
      },
      "geometry": {
        "type": "Point",
        "coordinates": [
          8.641315698623657,
          49.85996094836533
        ]
      }
    },
    {
      "type": "Feature",
      "properties": {
        "category": "playground",
        "name": "Spielplatz"
      },
      "geometry": {
        "type": "Point",
        "coordinates": [
          8.639797568321228,
          49.85753322041002
        ]
      }
    },
    {
      "type": "Feature",
      "properties": {
        "category": "playground",
        "name": "Spielplatz"
      },
      "geometry": {
        "type": "Point",
        "coordinates": [
          8.64047884941101,
          49.85909292859068
        ]
      }
    },
    {
      "type": "Feature",
      "properties": {
        "name": "Spielplatz",
        "category": "playground"
      },
      "geometry": {
        "type": "Point",
        "coordinates": [
          8.63974392414093,
          49.859182843713626
        ]
      }
    },
    {
      "type": "Feature",
      "properties": {
        "category": "park",
        "name": "Ingelheimer Garten"
      },
      "geometry": {
        "type": "Polygon",
        "coordinates": [
          [
            [
              8.641412258148193,
              49.86075978943792
            ],
            [
              8.640221357345581,
              49.860012821563224
            ],
            [
              8.641465902328491,
              49.85986066002477
            ],
            [
              8.641675114631653,
              49.86067679357768
            ],
            [
              8.641412258148193,
              49.86075978943792
            ]
          ]
        ]
      }
    },
    {
      "type": "Feature",
      "properties": {
        "category": "park",
        "name": "Akaziengarten"
      },
      "geometry": {
        "type": "Polygon",
        "coordinates": [
          [
            [
              8.63698661327362,
              49.862385096299604
            ],
            [
              8.637313842773438,
              49.862028916708155
            ],
            [
              8.63501787185669,
              49.861226638495225
            ],
            [
              8.635151982307434,
              49.8610848551844
            ],
            [
              8.634669184684753,
              49.86089465740671
            ],
            [
              8.63499104976654,
              49.86024797936188
            ],
            [
              8.63598346710205,
              49.8601615244219
            ],
            [
              8.637346029281616,
              49.86093269702214
            ],
            [
              8.637689352035522,
              49.86070791704198
            ],
            [
              8.63893926143646,
              49.86146870660084
            ],
            [
              8.637667894363403,
              49.86228827103948
            ],
            [
              8.637474775314331,
              49.86255799806713
            ],
            [
              8.63698661327362,
              49.862385096299604
            ]
          ]
        ]
      }
    },
    {
      "type": "Feature",
      "properties": {
        "name": "Heinrich-Heine-Schule",
        "category": "school"
      },
      "geometry": {
        "type": "Polygon",
        "coordinates": [
          [
            [
              8.640570044517517,
              49.85634697848707
            ],
            [
              8.640623688697813,
              49.85628126744183
            ],
            [
              8.640612959861755,
              49.85622247327303
            ],
            [
              8.641546368598938,
              49.85601842236736
            ],
            [
              8.641809225082397,
              49.85669628306959
            ],
            [
              8.641777038574217,
              49.856786202652444
            ],
            [
              8.641616106033325,
              49.8568104117423
            ],
            [
              8.640570044517517,
              49.85634697848707
            ]
          ]
        ]
      }
    },
    {
      "type": "Feature",
      "properties": {
        "category": "school",
        "name": "Wilhelm-Leuschner-Schule"
      },
      "geometry": {
        "type": "Polygon",
        "coordinates": [
          [
            [
              8.635382652282715,
              49.85904105440515
            ],
            [
              8.635554313659668,
              49.85887505663724
            ],
            [
              8.635709881782532,
              49.85883009881027
            ],
            [
              8.63874077796936,
              49.85870214168919
            ],
            [
              8.638815879821776,
              49.85906872064436
            ],
            [
              8.63900363445282,
              49.85923125947977
            ],
            [
              8.63825261592865,
              49.85973616386416
            ],
            [
              8.637667894363403,
              49.859435296818326
            ],
            [
              8.637351393699646,
              49.859649708008334
            ],
            [
              8.636788129806519,
              49.85929696651336
            ],
            [
              8.636546730995178,
              49.85929350825066
            ],
            [
              8.636203408241272,
              49.85931425782316
            ],
            [
              8.63599956035614,
              49.859359215199596
            ],
            [
              8.635881543159485,
              49.85941108904356
            ],
            [
              8.635382652282715,
              49.85904105440515
            ]
          ]
        ]
      }
    }
  ]
}
